{
	"panel": {
		"modal-btn-ban": "Banear",
		"modal-btn-kick": "Kickear",
		"modal-btn-warn": "Advertir",
		"modal-btn-cancel": "Cancelar",
		"modal-btn-confirm": "Confirmar",
		"modal-btn-share": "Compartir",
		"modal-btn-import": "Importar",
		"modal-btn-export": "Exportar",
		"modal-btn-save": "Guardar",
		"modal-btn-close": "Cerrar",
		"placeholder-serial-key": "Clave de Serie",
		"notification-screenshots-cleared": "Capturas de pantalla eliminadas.",
		"notification-no-access-to-this-section": "No tienes acceso a esta sección",
		"notification-redeem-license-already-has-license": "Ya tienes una licencia activa!",
		"notification-redeem-license-invalid-key": "No existe una licencia con ese número de serial. Comprueba que has introducido la clave correcta e inténtalo de nuevo.",
		"notification-redeem-license-already-claimed": "Esa licencia ya ha sido reclamada. Por favor, compruebe su key e inténtelo de nuevo.",
		"notification-redeem-license-successfully-claimed": "Su licencia ha sido activada con éxito. Expira ^a%s^7.",
		"notification-extend-license-no-license": "No tienes una licencia activa! Por favor, canjee primero una clave.",
		"notification-extend-license-invalid-key": "No existe ninguna licencia para esa clave de serie. Asegúrese de que ha introducido la clave correcta y vuelva a intentarlo.",
		"notification-extend-license-already-claimed": "Esa licencia ya ha sido reclamada. Por favor, compruebe su clave de serie e inténtelo de nuevo.",
		"notification-extend-license-never-expires": "Su licencia no caduca nunca!",
		"notification-extend-license-successfully-extended": "Su licencia ha sido ampliada con éxito! Expira ^a%s^7.",
		"notification-language-code-changed": "Has cambiado el idioma a ^a%s^7.%s",
		"notification-requesting-identifiers": "Solicitando identificadores...",
		"notification-failed-to-fetch-identifiers": "No se han podido obtener los identificadores. Por favor, inténtelo de nuevo...",
		"notification-language-code-expires": " (Esto se restablecerá al expirar la sesión.)",
		"notification-server-deleted": "Servidor eliminado.",
		"notification-no-server": "Ese servidor no existe!",
		"notification-ban-doesnt-exist": "Ese baneo no existe!",
		"notification-you-cannot-remove-this-ban": "No puedes eliminar este baneo.",
		"notification-only-owner-may-do-this": "Sólo el propietario de la licencia puede hacer esto!",
		"notification-no-access-to-server": "No tienes acceso a este servidor!",
		"notification-no-access-to-section": "No tienes acceso a esta sección!",
		"notification-no-options-selected": "No se ha seleccionado ninguna opción!",
		"notification-server-not-online": "El servidor no está en línea. Por favor, asegúrese de que el anticheat está funcionando y el servidor está en marcha.",
		"notification-no-players-online": "El servidor no tiene actualmente ningún jugador. La lista aparecerá cuando haya al menos un jugador.",
		"notification-bans-cleared": "Los baneos de este servidor han sido borrados.",
		"notification-config-reset": "La configuración de este servidor ha sido restablecida.",
		"notification-share-token-doesnt-exist": "Ese share token no existe. Compruebe la ortografía y vuelva a intentarlo.",
		"notification-token-%s-generated-expires-%s": "Tu share token es ^a%s ^7expirará en ^a%s^7.",
		"notification-config-imported": "Se ha importado con éxito la configuración del token!",
		"notificación-no-servidores-seleccionados-para-importar": "¡Debes seleccionar al menos un servidor del que importar bans!",
		"notification-bans-imported-successfully": "¡Prohibiciones importadas con éxito!",
		"navbar-search-servers": "Buscar un servidor...",
		"search-no-server-found": "No se ha encontrado ningún servidor",
		"search-no-servers-found": "No se ha encontrado ningún servidor",
		"profile-log-out": "Cerrar sesión",
		"sidebar-title-main": "Main",
		"sidebar-link-title-dashboard": "Dashboard",
		"sidebar-link-title-faq": "FAQ",
		"sidebar-link-title-install-guide": "Guía de instalación",
		"sidebar-link-title-admin": "Admin",
		"sidebar-sub-title-overview": "Visión general",
		"sidebar-sub-title-bans": "Bans",
		"sidebar-sub-title-logs": "Logs",
		"sidebar-sub-title-users": "Usuarios",
		"sidebar-sub-title-generate": "Generar",
		"sidebar-title-viewing-server": "Viendo servidor: %s",
		"sidebar-sub-title-server-settings": "Ajustes",
		"sidebar-sub-title-server-screenshots": "Capturas de pantalla",
		"sidebar-title-your-servers": "Sus servidores",
		"sidebar-title-no-servers": "No hay servidores",
		"sidebar-title-purchase-license": "Comprar Licencia",
		"sidebar-title-license-expired": "Licencia caducada",
		"sidebar-title-license-revoked": "Licencia anulada",
		"sidebar-title-servers-you-have-access-to": "Servidores a los que tienes acceso",
		"sidebar-sub-title-download": "Descargar",
		"sidebar-sub-title-extend": "Extender",
		"sidebar-sub-title-redeem": "Canjear",
		"sidebar-sub-title-extend-license": "Extender Licencia",
		"sidebar-sub-title-redeem-key": "Canjear clave",
		"sidebar-title-your-license-expires": "Tu licencia expira: %s",
		"sidebar-title-extend-your-license": "Extiende tu licencia <a href='/store' forced='true'>aquí</a>",
		"sidebar-sub-notify-no-servers": "Esta lista se llenará una vez que el anticheat se cargue en un servidor.",
		"page-admin-overview-card-title-claimed-licenses": "Licencias canjeadas",
		"page-admin-overview-card-title-unique-bans": "Baneos únicos",
		"page-admin-overview-card-title-global-bans": "Baneos globales",
		"page-admin-overview-card-title-unique-servers": "Servidores únicos",
		"page-admin-overview-card-title-all-servers": "Todos los servidores",
		"page-admin-overview-card-tr-license-id": "ID de licencia",
		"page-admin-overview-card-tr-license-owner": "Propietario de la licencia",
		"page-admin-overview-card-tr-license-uid": "UID de la licencia",
		"page-admin-overview-card-tr-server-name": "Nombre del servidor",
		"page-admin-overview-card-tr-server-uid": "UID del servidor",
		"page-admin-overview-card-tr-server-ip": "IP del servidor",
		"page-admin-overview-card-tr-server-status": "Estado del servidor",
		"page-admin-overview-card-tr-server-status-online": "Online",
		"page-admin-overview-card-tr-server-status-offline": "Offline",
		"page-admin-overview-card-tr-player-count": "Jugadores",
		"page-admin-overview-card-tr-server-version": "Versión del Servidor",
		"page-admin-overview-card-title-online-servers": "Servidores Online",
		"page-admin-overview-card-title-online-players": "Jugadores en línea",
		"page-admin-overview-card-tr-first-seen": "Visto por primera vez",
		"page-download-text-current-%s-version-%s": "Versión actual %s: %s",
		"page-download-title-button": "Descargar archivos",
		"page-extend-title": "Ampliar licencia",
		"page-extend-tooltip-key": "Por favor, introduzca la clave que ha recibido por correo electrónico",
		"page-extend-placeholder-key": "Clave",
		"page-extend-button-submit": "Ampliar licencia",
		"page-main-title": "Panel de control",
		"page-main-sub-license-expired": "Tu licencia ha expirado! Extiéndela para reactivarla.",
		"page-main-sub-license-revoked": "Su licencia ha sido anulada. El 95% de las veces esto se debe a una comprobación automática de infracción, por favor, póngase en contacto con el servicio de asistencia.",
		"page-main-sub-no-license": "No tienes una licencia activa! Considera comprar una <a href='/store' forced='true'>aquí</a> para usar el anticehat.",
		"page-faq-title": "Preguntas frecuentes (FAQ)",
		"page-faq-card-title": "FAQ",
		"page-redeem-title": "Canjear Licencia",
		"page-redeem-tooltip-key": "Introduzca la clave que ha recibido por correo electrónico.",
		"page-redeem-placeholder-key": "Clave",
		"page-redeem-button-submit": "Canjear Clave",
		"page-admin-bans-title": "Baneos Globales",
		"page-admin-bans-card-title": "Jugadores Baneados",
        "page-admin-bans-card-tr-ban-type": "Tipo de Baneo",
		"page-admin-bans-card-tr-ban-id": "ID de Baneo",
		"page-admin-bans-card-tr-ban-rejection-id": "ID de baneo",
		"page-admin-bans-card-tr-ban-identifiers": "Identificadores de Baneo",
		"page-admin-bans-card-tr-ban-name": "Nombre del Baneo",
		"page-admin-bans-card-tr-ban-reason": "Razón del Baneo",
		"page-admin-bans-card-tr-ban-additionals": "Información adicional",
		"page-admin-bans-card-tr-ban-date": "Baneado En",
		"page-admin-bans-card-tr-ban-actions": "Acciones",
		"page-admin-bans-modal-title": "Identificadores de baneo (Para: %s)",
		"page-admin-bans-modal-no-identifiers": "No hay identificadores que mostrar.",
		"page-admin-bans-modal-close": "Cerrar",
		"page-admin-logs-title": "Registro de eventos",
		"page-admin-logs-button-title": "Borrar registros",
		"page-admin-logs-modal-sub-are-you-sure": "¿Estás seguro de que quieres hacer esto? ¡Esta acción es irreversible!",
		"page-admin-logs-modal-button-submit": "Borrar",
		"page-admin-logs-modal-button-cancel": "Cancelar",
		"page-admin-logs-card-title": "Logs",
		"page-admin-logs-card-sub-fetching-logs": "Obteniendo logs...",
		"page-admin-logs-card-sub-no-logs": "No hay logs disponibles para mostrar",
		"page-admin-logs-card-sub-cleared-successfully": "¡Logs eliminados con éxito!",
		"page-admin-users-title": "Usuarios con licencia",
		"page-admin-users-card-title-all-users": "Todos los usuarios",
		"page-admin-users-card-tr-license-id": "ID de licencia",
		"page-admin-users-card-tr-discord": "Discord",
		"page-admin-users-card-tr-servers": "Sus Servidores",
		"page-admin-users-card-tr-license-revoked": "Licencia anulada",
		"page-admin-users-card-tr-license-expires": "Licencia expira",
		"page-admin-users-view-title": "Usuario - %s",
		"page-admin-users-view-btn-revoke-license": "Anular licencia",
		"page-admin-users-view-btn-reinstate-license": "Restablecer licencia",
		"page-admin-users-view-btn-go-back": "Volver",
		"page-admin-users-view-card-title": "Información del usuario",
		"page-admin-users-view-card-license-expires": "^aLicencia caduca: ^7%s",
		"page-admin-users-view-card-license-id": "^aIdentificación de la licencia: ^7%d",
		"page-admin-users-view-card-license-uid": "^aUID de la licencia: ^7%s",
		"page-admin-users-view-card-license-key": "^aClave de la licencia: ^7%s",
		"page-admin-users-view-card-license-max-servers": "^aServidores máximos: ^7%d",
		"page-admin-users-view-btn-decrease-servers": "Disminuir",
		"page-admin-users-view-btn-increase-servers": "Aumentar",
		"page-server-main-title": "<span>%s</span> ^g[^b%s^g]^7 - Principal",
		"page-server-main-btn-delete-server": "Borrar servidor",
		"page-server-main-modal-delete-server-body": "¿Está seguro de que desea eliminar los datos de este servidor? Esta acción no se puede revertir!",
		"page-server-main-card-total-bans": "Baneos Totales",
		"page-server-main-card-global-bans": "Baneos globales",
		"page-server-main-card-player-list": "Jugadores en línea",
		"page-server-main-card-player-list-no-active-players": "Actualmente no hay jugadores en línea",
		"page-server-main-card-player-list-table-id": "ID",
		"page-server-main-card-player-list-table-name": "Nombre",
		"page-server-main-card-player-list-table-steamid": "SteamID",
		"page-server-main-card-player-list-table-ping": "Ping",
		"page-server-main-card-player-list-table-actions": "Actions",
		"page-server-main-card-player-list-actions-ban": "Banear Jugador",
		"page-server-main-card-player-list-actions-kick": "Expulsar Jugador",
		"page-server-main-card-player-list-actions-warn": "Advertir Jugador",
		"page-server-main-card-player-list-actions-screenshot": "Capturar pantalla del Jugador",
		"page-server-bans-title": "<span>%s</span> ^g[^b%s^g]^7 - Baneos",
		"page-server-bans-btn-clear-bans": "Borrar Baneos",
		"page-server-bans-btn-import-bans": "Importar Baneos",
		"page-server-bans-btn-offline-ban": "Banear sin conexión",
		"page-server-bans-modal-clear-bans-body": "¿Estás seguro de que quieres borrar los baneos de este servidor? Esta acción no se puede revertir",
		"page-server-bans-modal-import-bans-body": "Selecciona los servidores de los que quieres importar baneos",
		"page-server-bans-modal-import-ans-no-bans": "No tienes bans de otros servidores para importar",
		"page-server-bans-unknown-server": "Servidor Desconocido (%s)",
		"page-server-bans-table-banned-players": "Jugadores Baneados",
		"page-server-bans-table-type": "Tipo",
		"page-server-settings-title": "<span>%s</span> ^g[^b%s^g]^7 - Ajustes",
		"page-server-settings-btn-reset-config": "Reestablecer Configuración",
		"page-server-settings-btn-share-config": "Compartir Configuración",
		"page-server-settings-btn-import-config": "Importar Configuración",
		"page-server-settings-modal-reset-config-body": "¿Estás seguro de que quieres restablecer tu configuración? Esta acción no se puede revertir",
		"page-server-settings-modal-share-config-body": "¡Seleccionar todo incluirá datos sensibles! No comparta esto fuera de su servidor",
		"page-server-settings-modal-share-config-body-fetching": "Fetching share token...",
		"page-server-settings-modal-import-config-body": "Por favor, introduzca el token de la configuración compartida a continuación",
		"page-server-settings-modal-import-config-body-fetching": "Obteniendo configuración del token...",
		"page-server-settings-card-hover-over-each-element-for-a-description": "Pasa el ratón por encima de cada opción para ver una descripción de para qué sirve",
		"page-server-screenshots-title": "<span>%s</span> ^g[^b%s^g]^7 - Capturas de Pantalla",
		"page-server-screenshots-btn-wipe-screenshots": "Borrar Capturas de Pantalla",
		"page-server-screenshots-modal-wipe-screenshots-body": "¿Estás seguro de que quieres borrar tus capturas de pantalla? Esta acción no se puede revertir",
		"page-server-screenshots-modal-screenshots-wiped": "Capturas de pantalla borradas",
		"page-server-screenshots-card-total-screenshots": "Capturas Totales",
		"page-server-screenshots-table-all-screenshots": "Todas las Capturas",
		"page-server-screenshots-modal-viewing-%s": "Viendo captura: %s",
		"page-screenshots-card-tr-screenshot-name": "Nombre de la captura de pantalla",
		"page-screenshots-card-tr-screenshot-from": "Captura de pantalla de",
		"page-screenshots-card-tr-screenshot-uploaded": "Subido en",
		"page-screenshots-card-tr-screenshot-actions": "Acciones",
		"input-ban-reason-title": "Razón de Baneo",
		"input-ban-reason-text": "Introducir razón de baneo",
		"input-kick-reason-title": "Razón de Expulsión",
		"input-kick-reason-text": "Introduce la razón de la patada",
		"input-warn-reason-title": "Razón de Advertencia",
		"input-warn-reason-text": "Introducir motivo de advertencia",
		"page-settings-language-webhooks_ban": "El webhook para publicar todos los mensajes relacionados con los baneos",
		"page-settings-language-webhooks_kick": "El webhook para publicar todos los mensajes relacionados con los kickeos",
		"page-settings-language-webhooks_warn": "El webhook en el que publicar todos los mensajes relacionados con las advertencias",
		"page-settings-language-webhooks_info": "El webhook en el que publicar toda la información diversa",
		"page-settings-language-webhooks_adminactions": "El webhook en el que publicar todas las acciones de administración",
		"page-settings-language-no_steam_identifier": "El mensaje a mostrar cuando no se encuentra un identificador de Steam",
		"page-settings-language-no_discord_identifier": "El mensaje a mostrar cuando no se encuentra un identificador de Discord",
		"page-settings-language-not_in_discord_server": "El mensaje a mostrar cuando el usuario no está en su servidor de Discord",
		"page-settings-language-profile_must_be_public": "El mensaje a mostrar cuando el usuario tiene un perfil de Steam privado",
		"page-settings-language-account_too_young": "El mensaje a mostrar cuando la cuenta de steam del usuario no cumple la edad mínima",
		"page-settings-language-bad_steam_name": "El mensaje a mostrar cuando el nombre de la cuenta de Steam del usuario tiene caracteres prohibidos",
		"page-settings-language-using_vpn": "El mensaje a mostrar cuando el usuario está utilizando una VPN",
		"page-settings-language-youre_banned": "El mensaje a mostrar cuando el usuario tiene un baneo registrado",
		"page-settings-language-banned_for_cheating": "El mensaje a mostrar cuando el usuario recibe un baneo por hacer trampas",
		"page-settings-language-kicked_for_cheating": "El mensaje a mostrar cuando el usuario recibe una patada por hacer trampas",
		"page-settings-language-banned_for_spam": "El mensaje a mostrar cuando el usuario recibe un baneo por hacer spam",
		"page-settings-language-kicked_for_spam": "El mensaje a mostrar cuando el usuario recibe una patada por spam",
		"page-settings-language-banned_for_blacklisted_word": "El mensaje a mostrar cuando el usuario recibe un baneo por usar una palabra de la lista negra",
		"page-settings-language-kicked_for_blacklisted_word": "El mensaje a mostrar cuando el usuario recibe un kickeo por usar una palabra de la lista negra",
		"generic-string-webhooks": "Webhooks",
		"generic-string-webhook": "Link de Webhook (Dejar vacío para desactivar)",
		"generic-string-block": "Bloquear",
		"generic-string-screenshot": "Captura de pantalla",
		"generic-string-ban": "Banear",
		"generic-string-kick": "Expulsar",
		"generic-string-warn": "Advertir",
		"generic-string-info": "Info",
		"generic-string-adminactions": "Acciones administrativas",
		"generic-string-on-blacklisted": "En la Blacklist",
		"generic-string-save": "Guardar",
		"generic-string-limit-%s": "Max %s",
		"generic-string-cooldown-%s": "Restablecer %s cuenta después",
		"generic-string-damage": "Daño",
		"generic-string-damage-tooltip": "¿Cuánto daño máximo puede hacer un usuario sin desencadenar una detección?",
		"generic-string-limit-%s-tooltip": "¿Cuántos %s debería poder spawnear un jugador antes de ser detectado?",
		"generic-string-cooldown-%s-tooltip": "¿Cuántos segundos debería esperar el anticheat para restablecer los spawns del jugador %s?",
		"generic-string-block-spawn": "¿Debe el anticheat bloquear el spawn?",
		"generic-string-kick-spawn": "¿Debe el anticheat expulsar al usuario en el spawn?",
		"generic-string-ban-spawn": "¿Debe el anticheat banear al usuario en el spawn?",
		"generic-string-warn-spawn": "¿Debe el anticheat avisar al personal del jugador en el spawn?",
		"generic-string-screenshot-spawn": "¿Debe el anticheat hacer una captura de pantalla del jugador en el spawn?",
		"generic-string-block-limit": "¿Debe el anticheat bloquear los spawns en el límite?",
		"generic-string-kick-limit": "¿Debe el anticheat kickear al usuario en el límite?",
		"generic-string-ban-limit": "¿Debe el anticheat prohibir al usuario en el límite?",
		"generic-string-warn-limit": "¿Debe el anticheat avisar al personal del jugador en el límite?",
		"generic-string-screenshot-limit": "¿Debe el anticheat hacer una captura de pantalla al jugador en el límite?",
		"generic-string-on-limit": "En el Límite",
		"generic-string-on-use": "En uso",
		"generic-string-blacklisted-%s-tooltip": "Lista de %s en la lista negra. (separados por comas)",
		"generic-string-blacklisted-%s": "Lista negra %s",
		"generic-string-on-weapon-give": "On Weapon Give",
		"generic-string-on-weapon-take": "On Weapon Take",
		"generic-string-on-weapon-damage": "On Weapon Damage",
		"generic-string-use-blacklist-%s": "¿Debe el anticheat usar una lista negra para los spawns de %s? (Si se desactiva, se usa una lista blanca)",
		"generic-string-use-blacklist": "Usar Blacklist",
		"generic-string-block-all-%s": "¿Debe el anticheat cancelar todos los spawns de %s?",
		"generic-string-block-all": "Bloquear Todo",
		"generic-string-required": "Requerido",
		"generic-string-namecheck": "Comprobar nombre",
		"generic-string-namepattern": "Comprobar nombre",
		"generic-string-seperated-by-%s": "(separado por %s)",
		"generic-string-agecheck": "Comprobar edad de la cuenta",
		"generic-string-publiccheck": "Forzar perfiles públicos",
		"generic-string-minimumage": "Edad mínima de la cuenta",
		"generic-string-apikey": "Steam API Key",
		"generic-string-servercheck": "Comprobar si está en el servidor",
		"generic-string-invitelink": "Tu enlace de invitación al servidor",
		"generic-string-serverid": "Su ID de servidor",
		"generic-string-bottoken": "Tu Bot Token",
		"generic-string-dolog": "Registrar",
		"generic-string-blockvpns": "Bloquear VPNs",
		"generic-string-vpnbypass": "VPN SteamID Bypass",
		"generic-string-explosions": "Explosiones",
		"generic-string-language": "Idioma",
		"generic-string-blockall": "Bloquear Todo",
		"generic-string-useblacklist": "Usar Blacklist",
		"generic-string-onblacklist": "En la Blacklist",
		"generic-string-onlimit": "Sobre Límite",
		"generic-string-%slist": "%s Lista",
		"generic-string-%slimit": "%s Limite",
		"generic-string-%scooldown": "%s Restablecer Cooldown",
		"generic-string-object": "Objeto",
		"generic-string-objects": "Objetos",
		"generic-string-vehicle": "Vehículo",
		"generic-string-vehicles": "Vehículos",
		"generic-string-ped": "Ped",
		"generic-string-peds": "Peds",
		"generic-string-weapon": "Arma",
		"generic-string-weapons": "Armas",
		"generic-string-giveevent": "Al dar un arma",
		"generic-string-block-givevent": "¿Debe el anticheat bloquear el GiveWeapon?",
		"generic-string-kick-giveevent":  "¿Debe el anticheat kickear al usuario al dar el arma?",
		"generic-string-ban-givevent": "¿Debería el anticheat banear al usuario el dar un arma?",
		"generic-string-warn-givevent": "¿Debería el anticheat avisar al personal del jugador en la entrega del arma?",
		"generic-string-screenshot-givevent": "¿Debe el anticheat hacer una captura de pantalla del jugador al dar el arma?",
		"generic-string-takeevent": "Al quitar un arma",
		"generic-string-block-takeevent": "¿Debe el anticheat bloquear la toma del arma?",
		"generic-string-kick-takeevent": "¿Debe el anticheat kickear al usuario al quitar un arma?",
		"generic-string-ban-takeevent": "¿Debe el anticheat banaer al usuario al quitar un arma?",
		"generic-string-warn-takeevent": "¿Debe el anticheat advertir al personal del jugador al quitar un arma?",
		"generic-string-screenshot-takeevent": "¿Debe el anticheat hacer una captura de pantalla del jugador al quitar un arma?",
		"generic-string-damageevent": "Al hacer daño",
		"generic-string-block-damageevent": "¿Debe el anticheat bloquear el evento si su daño es demasiado alto?",
		"generic-string-kick-damageevent": "¿Debe el anticheat expulsar al usuario si su daño es demasiado alto?",
		"generic-string-ban-damageevent": "¿Debe el anticheat banear al usuario si su daño es demasiado alto?",
		"generic-string-warn-damageevent": "¿Debe el anticheat avisar al personal del jugador si su daño es demasiado alto?",
		"generic-string-block-use": "¿Debe el anticheat bloquear el evento de ClearPedTasks?",
		"generic-string-kick-use": "¿Debe el anticheat kickear al usuario que ejecute el evento de ClearPedTasks?",
		"generic-string-ban-use": "¿Debe el anticheat banear al usuario que ejecute el evento de ClearPedTasks?",
		"generic-string-warn-use": "¿Debe el anticheat avisar al personal del jugador si ejecuta el evento de ClearPedTasks?",
		"generic-string-particle": "Partícula",
		"generic-string-particles": "Partículas",
		"generic-string-useevent": "En uso",
		"generic-string-clearpedtasks": "Clear Ped Tasks",
		"generic-string-onplayer": "En el objetivo del jugador",
		"generic-string-security": "Seguridad",
		"generic-string-triggerprotection": "Parchear Triggers",
		"generic-string-triggerprotection-tooltip": "¿Debe el anticheat proteger los triggers explotables conocidos? (Requiere reiniciar el servidor)",
		"generic-string-warnmultiplebans-tooltip": "¿Debería el anticheat avisar a los administradores si alguien tiene múltiples bans en el registro?",
		"generic-string-warnmultiplebans": "Advertir al personal sobre los baneos múltiples",
		"generic-string-networkbans-tooltip": "¿Debería el anticheat utilizar baneos entre servidores?",
		"generic-string-networkbans": "Usar baneos de red",
		"generic-string-globalbans-tooltip": "¿Debería el anticheat utilizar prohibiciones de red globales?",
		"generic-string-globalbans": "Usar baneos globales",
		"generic-string-honeypottrigger": "Trigger Trampa",
		"generic-string-honeypottriggers": "Triggers Trampa",
		"generic-string-keys": "Keys",
		"generic-string-kick-keypressed": "Should the anticheat kick the user on key press?",
		"generic-string-ban-keypressed": "Should the anticheat ban the user on key press?",
		"generic-string-warn-keypressed": "Should the anticheat warn staff of the player on key press?",
		"generic-string-screenshot-keypressed": "Should the anticheat screenshot the player on key press?",
		"generic-string-chat": "Chat",
		"generic-string-prechecks": "Prechecks",
		"generic-string-prechecks-log-connect": "Log On Connect",
		"generic-string-prechecks-log-disconnect": "Log On Disconnect",
		"generic-string-prechecks-blockvpns": "Block VPNs",
		"generic-string-prechecks-steam": "Steam",
		"generic-string-prechecks-discord": "Discord",
		"generic-string-playerdisconnect": "Player Disconnect",
		"generic-string-panel": "Panel",
		"generic-string-admins": "Admins",
		"generic-string-moderators": "Moderators",
		"generic-string-show-player-list": "Show Active Players",
		"generic-string-tooltip-show-player-list": "Should the panel show the players on the server?",
		"generic-string-tooltip-admins": "List of admins that can access the panel (DiscordID, seperated by comma)",
		"generic-string-tooltip-moderators": "List of moderators that can access the panel (DiscordID, seperated by comma)",
		"generic-string-tooltip-blockall-%s": "Should the anticheat block all %s spawns?",
		"generic-string-tooltip-ban-blacklist-%s": "Should the anticheat ban on a blacklisted %s?",
		"generic-string-tooltip-ban-limit-%s": "Should the anticheat ban on exceeding %s limit?",
		"generic-string-tooltip-kick-blacklist-%s": "Should the anticheat kick on a blacklisted %s?",
		"generic-string-tooltip-kick-limit-%s": "Should the anticheat kick on exceeding %s limit?",
		"generic-string-tooltip-warn-blacklist-%s": "Should the anticheat warn on a blacklisted %s?",
		"generic-string-tooltip-warn-limit-%s": "Should the anticheat warn on exceeding %s limit?",
		"generic-string-tooltip-screenshot-blacklist-%s": "Should the anticheat screenshot on a blacklisted %s?",
		"generic-string-tooltip-screenshot-limit-%s": "Should the anticheat screenshot on exceeding %s limit?",
		"generic-string-vpn": "VPN Whitelist",
		"generic-string-check-name": "Check Name",
		"generic-string-check-age": "Check Account Age",
		"generic-string-name-pattern": "Name Pattern",
		"generic-string-minimum-age": "Account Minimum Age",
		"generic-string-api-key": "API Key",
		"generic-string-check-server": "Check In Server",
		"generic-string-server-id": "Server ID",
		"generic-string-bot-secret": "Bot Secret",
		"generic-string-tooltip-steam-required": "Should the anticheat require people to have steam running to join?",
		"generic-string-tooltip-steam-check-name": "Should the anticheat check people's steam names?",
		"generic-string-tooltip-steam-name-pattern": "What should be the name pattern check look for?",
		"generic-string-tooltip-steam-check-age": "Should the anticheat check people's steam account age?",
		"generic-string-tooltip-steam-minimum-age": "What should be the minimum age account allowed to play? (in seconds)",
		"generic-string-tooltip-steam-api-key": "Your steam api key",
		"generic-string-tooltip-discord-required": "Should the anticheat require people to have discord running to join?",
		"generic-string-tooltip-discord-check-server": "Should the anticheat require people to be in the discord server to join?",
		"generic-string-tooltip-discord-server-id": "Your server id",
		"generic-string-tooltip-discord-bot-secret": "Your bot's token",
		"failed-to-parse-config-%s": "Config parse failed: %s"
	},
	"server": {
		"checking-for-new-versions": "Checking for new versions...",
		"no-new-versions-found": "No new versions found.",
		"error-occured-while-protecting-%s": "Error occured while protecting %{yellow}%s %{red}%s",
		"%s-is-not-a-clientside-resource": "%{yellow}%s %{reset}is %{red}not %{reset}a %{blue}clientside %{reset}resource.",
		"removed-payload-from-%s": "Removed payload from %{yellow}%s%{reset}.",
		"setting-up-core": "Setting up core...",
		"fetching-config": "Fetching config...",
		"loading-version-%s": "Loading version %{yellow}%s",
		"your-license-expires-%s": "Your license expires: %{yellow}%s",
		"initialized-database-in-%d": "Successfully initialized database in %{yellow}%dms%{reset}.",
		"config-updated-in-%d": "Received updated config from panel in %{yellow}%dms%{reset}.",
		"connecting-%s-has-connected": "%{white}Player %{yellow}%s %{white}(%{yellow}%s%{white}) has connected.",
		"connecting-%s-has-disconnected-%s": "%{white}Player %{yellow}%s %{white}(%{yellow}%s%{white}) has disconnected. (%{yellow}%s%{white})",
		"connecting-%s-has-multiple-bans-on-record-%s": "%{white}Player %{yellow}%s %{white}(%{yellow}%s%{white}) has multiple bans (%{yellow}%s%{white]) on record.",
		"connecting-loading-this-may-take-a-moment": "Loading... This may take a moment.",
		"connecting-loading-connection-rejected-%s": "Connection Rejected: %s",
		"kicked-from-server-for-%s-by-%s": "Kicked from server: %s (%s)",
		"%s-%s-was-kicked-for-%s": "%{yellow}%s %{white}(%{yellow}%s%{white}) was kicked for: %{yellow}%s%{reset}",
		"%s-%s-kicked-%s-%s-for-%s": "^5%s ^7(^6%s^7) kicked ^5%s ^7(^6%s^7) for ^3%s^7",
		"%s-%s-froze-%s-%s": "^5%s ^7(^6%s^7) froze ^5%s",
		"%s-%s-unfroze-%s-%s": "^5%s ^7(^6%s^7) unfroze ^5%s",
		"%s-%s-was-banned-for-%s": "%{yellow}%s %{white}(%{yellow}%s%{white}) was banned for: %{yellow}%s%{reset}",
		"%s-%s-banned-%s-%s-for-%s": "^5%s ^7(^6%s^7) banned ^5%s ^7(^6%s^7) for ^3%s^7",
		"%s-%s-banned-%s-for-%s": "^5%s ^7(^6%s^7) banned ^5%s for ^3%s^7",
		"%s-%s-warned-%s-%s-for-%s": "^5%s ^7(^6%s^7) warned ^5%s ^7(^6%s^7) for ^3%s^7",
		"connecting-progress-sid-checking": "Checking if steam is running...",
		"connecting-progress-name-checking": "Checking steam name...",
		"connecting-progress-profile-checking": "Checking steam profile...",
		"connecting-progress-did-checking": "Checking if discord is running...",
		"connecting-progress-dserver-checking": "Checking if in discord server...",
		"connecting-progress-checking-for-vpn": "Checking if you're on a vpn...",
		"connecting-progress-checking-ban": "Checking if banned...",
		"connecting-loading-name-pattern-empty": "Your config is missing a name check character list! Please enter one via the panel to use this feature.",
		"connecting-loading-no-steam-api-key": "Your config is missing a steam api key! Please enter one via the panel to use this subset of features.",
		"connecting-loading-no-discord-server-id": "Your config is missing a discord server id! Please enter one via the panel to use this feature.",
		"connecting-loading-no-discord-bot-token": "Your config is missing a discord bot token! Please enter one via the panel to use this feature.",
		"triggers-checking-triggers": "Checking known exploitable triggers...",
		"generic-reason-string": "No reason specified.",
		"player-doesnt-exist": "That player does not exist!",
		"player-has-been-kicked": "Player has been kicked.",
		"player-has-been-banned": "Player has been banned.",
		"warning-%s": "^1[Warning] ^7%s",
		"player-has-been-warned": "Player has been warned.",
		"webhook-%s-is-being-rate-limited-retrying-in-%s-seconds": "Webhook %{yellow}%s %{reset}is currently being rate limited. The rate limit resets in %{yellow}%s %{reset}seconds.",
		"webhook-%s-got-an-invalid-response-%d": "Webhook %{yellow}%s %{reset}got an invalid code %{red}%d%{reset}.",
		"player-is-already-being-screenshotted": "Player is already being screenshotted!",
		"screenshotting-player": "Screenshotting player. (This may take a moment.)",
		"player-screenshot-failed-%s": "Failed to screenshot player. (%s)",
		"player-screenshot-%s-%s": "Screenshot of %s (%s)",
		"%s-%s-screenshotted-%s-%s": "^5%s ^7(^6%s^7) requested a screengrab of ^5%s ^7(^6%s^7)",
		"screenshotting-all-players": "Screenshotting all players. (This will take a moment.)",
		"spectating-%s": "Spectating %s",
		"%s-%s-teleported-%s-%s": "^5%s ^7(^6%s^7) teleported ^5%s ^7(^6%s^7)",
		"%s-%s-teleported-to-%s-%s": "^5%s ^7(^6%s^7) teleported to ^5%s ^7(^6%s^7)",
		"player-has-been-brought": "Player has been brought.",
		"teleported-to-player": "Teleported to player.",
		"frozen-player-%s": "Frozen %s",
		"unfrozen-player-%s": "Unfroze %s",
		"you-have-been-frozen": "You have been frozen.",
		"you-have-been-unfrozen": "You have been unfrozen.",
		"peds-wiped": "Peds wiped.",
		"%s-%s-wiped-all-peds": "^5%s ^7(^6%s^7) wiped all ^3peds^7.",
		"entities-wiped": "Entities wiped.",
		"%s-%s-wiped-all-entities": "^5%s ^7(^6%s^7) wiped all ^3entities^7.",
		"vehicles-wiped": "Vehicles wiped.",
		"%s-%s-wiped-all-vehicles": "^5%s ^7(^6%s^7) wiped all ^3vehicles^7.",
		"successfully-banned": "Successfully banned.",
		"invalid-player": "Invalid Player.",
		"server-exiting": "Killing server process...",
		"fetching-license-duration": "Fetching license duration. This may take a moment...",
		"player-%s-%d-was-flagged-for-possibly-cheating": "Player ^6%s ^7(^3%d^7) was flagged for possibly cheating.",
		"player-%s-%d-is-using-modified-weapon-damage-%d-%d": "Player ^6%s ^7(^3%d^7) is using modified weapon damage. Turn this off in the text config if you use weapon metas. (^5%d^7/^5%d^7)",
		"player-%s-%d-created-a-blacklisted-explosion-of-type-%s": "Player ^6%s ^7(^3%d^7) created a blacklisted explosion of type ^3%s^7.",
		"player-%s-%d-exceeded-the-explosion-limit": "Player ^6%s ^7(^3%d^7) exceeded the explosion limit.",
		"player-%s-%d-created-a-blacklisted-%s-with-model-%s": "Player ^6%s ^7(^3%d^7) created a blacklisted %s with model ^3%s^7.",
		"player-%s-%d-exceeded-the-%s-limit": "Player ^6%s ^7(^3%d^7) exceeded the %s limit.",
		"player-%s-%d-attempted-to-give-%s-%d-weapon-%s": "Player ^6%s ^7(^3%d^7) attempted to give ^6%s ^7(^3%d^7) weapon ^3%s^7.",
		"player-%s-%d-attempted-to-take-%s-%d-weapons": "Player ^6%s ^7(^3%d^7) attempted to remove ^6%s ^7(^3%d^7)'s weapons.",
		"player-%s-%d-attempted-to-freeze-%s-%d": "Player ^6%s ^7(^3%d^7) attempted to freeze ^6%s ^7(^3%d^7).",
		"player-%s-%d-is-using-particle-effects": "Player ^6%s ^7(^3%d^7) is using particle effects.",
		"player-%s-%d-attempted-to-say-blacklisted-word-%s": "Player ^6%s ^7(^3%d^7) attempted to say blacklisted word ^3%s^7.",
		"player-%s-%d-is-spamming-chat": "Player ^6%s ^7(^3%d^7) is spamming chat.",
		"player-%s-%d-pressed-a-blacklisted-key-combination": "Player ^6%s ^7(^3%d^7) pressed a blacklisted key combination.",
		"player-%s-%d-spawned-a-blacklisted-weapon": "Player ^6%s ^7(^3%d^7) spawned a blacklisted weapon.",
		"player-%s-%d-may-be-noclipping": "Player ^6%s ^7(^3%d^7) may be noclipping.",
		"player-%s-%d-may-be-freecamming": "Player ^6%s ^7(^3%d^7) may be freecamming.",
		"player-%s-%d-may-be-using-aimassist": "Player ^6%s ^7(^3%d^7) may be using aimassist.",
		"player-%s-%d-may-be-aimbotting": "Player ^6%s ^7(^3%d^7) may be aimbotting.",
		"please-restart-your-server": "Please %{red}restart %{reset}your server.",
		"fxap-warning": "%{red}You have not finished installation! %{reset}For Event Protection, you must read the guide to avoid false bans!",
		"updated-%s": "Updated %{yellow}%s%{reset}.",
		"payload-not-installed": "That payload is not installed.",
		"removing-payload-from-%d-resource-%s": "Removing payload from %{yellow}%d %{reset}resource%s.",
		"installed-into-resource-%s": "Installed into resource %{yellow}%s%{reset}.",
		"invalid-module-%s": "Invalid module %{yellow}%s%{reset}.",
		"fetching-payload": "Fetching payload...",
		"dispatched-event-that-resource-%s-was-started": "Dispatched %{green}start %{reset}event for resource %{yellow}%s%{reset}.",
		"dispatched-event-that-resource-%s-was-stopped": "Dispatched %{red}stop %{reset}event for resource %{yellow}%s%{reset}.",
		"cannot-use-tokens-artifact-too-low": "Tokens cannot be used on this server as your artifacts are too old!",
		"restarted-resource-%s": "Restarted resource %{yellow}%s%{reset}.",
		"failed-to-open-file-%s-in-resource-%s-%d": "Failed to open file %{yellow}%s %{reset}in resource %{blue}%s %{reset}(Error: %{red}%d%{reset})",
		"installed-screenshot-version-%s": "Installed screenshot version %{yellow}%s%{reset}.",
		"protecting-resource-%s": "Protecting resource %{yellow}%s%{reset}.",
		"time-threshold-exceeded-for-screenshot-upload": "Time threshold exceeded while waiting for client to upload screenshot.",
		"player-disconnected-during-screenshot": "Player disconnected during screenshot.",
		"empty-response-from-client": "The client sent an empty url.",
		"discord-server-check-failed-code-%d-message-%s": "Discord server check failed, got code %{red}%d%{reset} with message %{yellow}%s%{reset}.",
		"word-year": "Year",
		"word-month": "Month",
		"word-week": "Week",
		"word-day": "Day",
		"word-hour": "Hour",
		"word-minute": "Minute",
		"word-second": "Second",
		"word-plural": "s"
	},
	"console": {
		"list-of-available-commands": "List of available commands:",
		"generic-description": "No description is available for this command.",
		"word-not": "not",
		"command-describe-help": "Lists all of the available commands",
		"command-describe-exit": "Kills the server process",
		"command-describe-duration": "Prints the duration of your license.",
		"command-describe-install": "Installs the anticheat [or specified module] into your resources.",
		"command-describe-remove": "Removes the anticheat [or specified module] from your resources.",
		"command-describe-status": "Gets the status of the anticheat [or specified module]",
		"command-describe-ban": "Bans a user that is online / offline.",
		"command-describe-screenshot": "Chooses which mode of screenshotting you want to use.",
		"invalid-module-%s": "Invalid module %{yellow}%s%{reset}.",
		"invalid-option-%s": "Invalid option %{yellow}%s%{reset}.",
		"module-%s-is-%s-%s-installed-%s": "Module %{yellow}%s %{reset}is %s%{%s}installed%s%{reset}.",
		"player-banned": "Player banned.",
		"invalid-command": "Please use %{yellow}pac help %{reset}to view the available commands.",
		"existing-identifiers-not-found": "Existing identifiers for this user do not exist! They may be able to evade the ban!",
		"command-%s-is-not-valid": "%{yellow}%s %{reset}is not a valid command. Use %{yellow}pac help %{reset}to view the available commands.",
		"failed-to-open-file-%s-in-resource-%s-%d": "Failed to open file %{yellow}%s %{reset}in resource %{blue}%s %{reset}(Error: %{red}%d%{reset})"
	},
	"triggers": {
		"societies-not-loaded": "There is no registered societies! Please ensure all resources are running and ensure %{yellow}%s %{reset}is the last to start.",
		"society-error-%s-doesnt-exist": "Player %s (%d) attempted to bill %s (%d) but society %{yellow}%s %{reset}doesn't exist!",
		"society-error-invalid-job": "Player %s (%d) attempted to bill %s (%d) but their job %{yellow}%s %{reset}doesn't match the society name %{yellow}%s%{reset}!",
		"society-log": "Player %s (%d) billed %s (%d) for %s [%d]",
		"thief-log": "Player %s (%d) stole %s [%d] (%s) from %s (%d)"
	},
	"webhooks": {
		"admin-action": "Admin Action",
		"admin-%s-%s-performed-action-%s": "Admin `%s (%s)` performed action `%s`.",
		"action-data": "Action Data",
		"warning": "Warning",
		"reason": "Reason",
		"admin": "Admin",
		"additionals": "Additionals",
		"offline-ban": "Offline Ban",
		"player-name": "Player Name",
		"player-identifiers": "Player Identifiers",
		"player-connecting": "Player Connecting",
		"player-disconnected": "Player Disconnected",
		"disconnect-reason": "Disconnect Reason",
		"screenshot": "Screenshot",
		"player-kicked": "Player Kicked",
		"player-banned": "Player Banned",
		"player-rejected": "Player Rejected",
		"ban-type": "Ban Type",
		"source": "Source",
		"name": "Name",
		"steam": "Steam",
		"steam-not-found": "Steam not found.",
		"discord": "Discord",
		"server-started": "Server Started",
		"running-version-%s": "Running version `%s`."
	},
	"version": {
		"pac_am-outdated": "Your version of the %{blue}Admin Menu%{reset} (%{yellow}%s%{reset}) is outdated. Please restart your server to receive the latest update. (%{yellow}%s%{reset})",
		"pac_cac-outdated": "Your version of the %{blue}Clientside Anticheat%{reset} (%{yellow}%s%{reset}) is outdated. Please run %{yellow}pac install%{reset} to receive the latest update. (%{yellow}%s%{reset})",
		"pac_loader-outdated": "Your version of the %{blue}Loader%{reset} (%{yellow}%s%{reset}) is outdated. Please redownload the anticheat to receive the latest update. (%{yellow}%s%{reset})",
		"pac_emd-outdated": "Your version of the %{blue}EMD%{reset} (%{yellow}%s%{reset}) is outdated. Please run %{yellow}pac install detector%{reset} to receive the latest update. (%{yellow}%s%{reset})",
		"pac_ep-outdated": "Your version of the %{blue}EMD%{reset} (%{yellow}%s%{reset}) is outdated. Please run %{yellow}pac install eventprotection%{reset} to receive the latest update. (%{yellow}%s%{reset})",
		"pac_sac-outdated": "Your version of the %{blue}Serverside Anticheat%{reset} (%{yellow}%s%{reset}) is outdated. Please restart your server to receive the latest update. (%{yellow}%s%{reset})"
	}
}
